{
	"name": "Tokyo Night",
	"comment": "Generated by Gogh",
	"foreground-color": "#C0CAF5",
	"background-color":"#1A1B26",
	"cursor-background-color": "#C0CAF5",
	"palette": [
		"#414868",
		"#F7768E",
		"#9ECE6A",
		"#E0AF68",
		"#7AA2F7",
		"#BB9AF7",
		"#7DCFFF",
		"#A9B1D6",
		"#414868",
		"#F7768E",
		"#9ECE6A",
		"#E0AF68",
		"#7AA2F7",
		"#BB9AF7",
		"#7DCFFF",
		"#C0CAF5"
	],
	"use-badge-color": false,
	"use-bold-color": false,
	"use-cursor-color": false,
	"use-highlight-color": false,
	"use-theme-colors": false
}
